majormode/__init__.py
majormode/mercurius/__init__.py
majormode/mercurius/client/__init__.py
majormode/mercurius/client/service/__init__.py
majormode/mercurius/client/service/place/__init__.py
majormode/mercurius/client/service/place/place_service.py
mercurius_restful_api_client_library-1.0.0.dist-info/METADATA
mercurius_restful_api_client_library-1.0.0.dist-info/WHEEL
mercurius_restful_api_client_library-1.0.0.dist-info/top_level.txt
mercurius_restful_api_client_library-1.0.0.dist-info/RECORD
