Metadata-Version: 2.1
Name: mercurius-restful-api-client-library
Version: 1.0.0
Summary: Mercurius RESTful API Client Python Library
Home-page: UNKNOWN
Author: Daniel CAUNE
Author-email: daniel.caune@majormode.com
License: Copyright (C) 2019, Majormode
Platform: any
Classifier: Development Status :: 5 - Production/Stable
Classifier: License :: OSI Approved :: MIT License
Classifier: Operating System :: OS Independent
Classifier: Programming Language :: Python
Classifier: Topic :: Software Development :: Libraries :: Python Modules
Requires-Python: >=3
Requires-Dist: mercurius-core-library
